asusrouter/__init__.py
asusrouter/__main__.py
asusrouter/asusrouter.py
asusrouter/config.py
asusrouter/connection.py
asusrouter/connection_config.py
asusrouter/const.py
asusrouter/error.py
asusrouter/py.typed
asusrouter/registry.py
asusrouter/modules/__init__.py
asusrouter/modules/access_point.py
asusrouter/modules/aimesh.py
asusrouter/modules/attributes.py
asusrouter/modules/aura.py
asusrouter/modules/client.py
asusrouter/modules/color.py
asusrouter/modules/connection.py
asusrouter/modules/const.py
asusrouter/modules/data.py
asusrouter/modules/data_finder.py
asusrouter/modules/data_transform.py
asusrouter/modules/ddns.py
asusrouter/modules/device.py
asusrouter/modules/firmware.py
asusrouter/modules/flags.py
asusrouter/modules/homeassistant.py
asusrouter/modules/identity.py
asusrouter/modules/ip_address.py
asusrouter/modules/led.py
asusrouter/modules/openvpn.py
asusrouter/modules/parental_control.py
asusrouter/modules/port_forwarding.py
asusrouter/modules/ports.py
asusrouter/modules/service.py
asusrouter/modules/source.py
asusrouter/modules/state.py
asusrouter/modules/system.py
asusrouter/modules/traffic.py
asusrouter/modules/vendor.py
asusrouter/modules/vpnc.py
asusrouter/modules/wireguard.py
asusrouter/modules/wlan.py
asusrouter/modules/endpoint/__init__.py
asusrouter/modules/endpoint/aura.py
asusrouter/modules/endpoint/command.py
asusrouter/modules/endpoint/devicemap.py
asusrouter/modules/endpoint/devicemap_const.py
asusrouter/modules/endpoint/error.py
asusrouter/modules/endpoint/ethernet_ports.py
asusrouter/modules/endpoint/firmware.py
asusrouter/modules/endpoint/firmware_note.py
asusrouter/modules/endpoint/firmware_note_aimesh.py
asusrouter/modules/endpoint/hook.py
asusrouter/modules/endpoint/hook_const.py
asusrouter/modules/endpoint/network.py
asusrouter/modules/endpoint/networkmapd.py
asusrouter/modules/endpoint/onboarding.py
asusrouter/modules/endpoint/port_status.py
asusrouter/modules/endpoint/rgb.py
asusrouter/modules/endpoint/state.py
asusrouter-1.21.0.dist-info/licenses/LICENSE
asusrouter-1.21.0.dist-info/licenses/NOTICE
asusrouter-1.21.0.dist-info/METADATA
asusrouter-1.21.0.dist-info/WHEEL
asusrouter-1.21.0.dist-info/top_level.txt
asusrouter-1.21.0.dist-info/RECORD
