Metadata-Version: 2.4
Name: asusrouter
Version: 1.21.0
Summary: API wrapper for communication with ASUSWRT-powered routers using HTTP protocol
Home-page: https://github.com/Vaskivskyi/asusrouter
Author-email: Yevhenii Vaskivskyi <yevhenii@vaskivskyi.com>
License-Expression: Apache-2.0
Project-URL: Homepage, https://asusrouter.vaskivskyi.com/
Project-URL: Source Code, https://github.com/Vaskivskyi/asusrouter
Project-URL: Bug Reports, https://github.com/Vaskivskyi/asusrouter/issues
Classifier: Development Status :: 3 - Alpha
Classifier: Intended Audience :: Developers
Classifier: Operating System :: OS Independent
Classifier: Programming Language :: Python :: 3.11
Classifier: Programming Language :: Python :: 3.12
Classifier: Programming Language :: Python :: 3.13
Classifier: Topic :: Software Development :: Libraries
Requires-Python: >=3.11.0
License-File: LICENSE
License-File: NOTICE
Requires-Dist: aiohttp>=3.8.1
Requires-Dist: urllib3>=1.26.14
Requires-Dist: xmltodict>=0.12.0
Dynamic: license-file
